waifuvault/__init__.py
waifuvault/waifumodels.py
waifuvault/waifuvault.py
waifuvault-1.5.7.dist-info/licenses/LICENSE
waifuvault-1.5.7.dist-info/METADATA
waifuvault-1.5.7.dist-info/WHEEL
waifuvault-1.5.7.dist-info/top_level.txt
waifuvault-1.5.7.dist-info/RECORD
