Metadata-Version: 2.4
Name: waifuvault
Version: 1.5.7
Summary: waifuVault Python API module
Author-email: Walker Aldridge <walker@waifuvault.moe>
Project-URL: Homepage, https://github.com/waifuvault/waifuVault-python-api
Project-URL: Issues, https://github.com/waifuvault/waifuVault-python-api/issues
Classifier: Programming Language :: Python :: 3
Classifier: License :: OSI Approved :: MIT License
Classifier: Operating System :: OS Independent
Requires-Python: >=3.10
License-File: LICENSE
Requires-Dist: requests
Requires-Dist: requests_toolbelt
Requires-Dist: aiohttp
Requires-Dist: asyncio
Provides-Extra: dev
Requires-Dist: pytest; extra == "dev"
Requires-Dist: pytest-mock; extra == "dev"
Requires-Dist: pytest-asyncio; extra == "dev"
Dynamic: license-file
